full_dia/__init__.py
full_dia/assemble.py
full_dia/calib.py
full_dia/cfg.py
full_dia/cross.py
full_dia/dataloader.py
full_dia/decoy.py
full_dia/deepmall.py
full_dia/deepmap.py
full_dia/fdr.py
full_dia/fxic.py
full_dia/library.py
full_dia/log.py
full_dia/main.py
full_dia/models.py
full_dia/polish.py
full_dia/quant.py
full_dia/refine.py
full_dia/scoring.py
full_dia/search.py
full_dia/tims.py
full_dia/utils.py
full_dia/alphatims/__init__.py
full_dia/alphatims/bruker.py
full_dia/alphatims/utils.py
full_dia/alphatims/ext/timsdata.dll
full_dia/alphatims/ext/timsdata.so
full_dia/cfg/default.yaml
full_dia/pretrained/deepbig_ys_fast.pt
full_dia/pretrained/deepcenter_ys_fast.pt
full_dia-1.0.2.dist-info/licenses/LICENSE
full_dia-1.0.2.dist-info/METADATA
full_dia-1.0.2.dist-info/WHEEL
full_dia-1.0.2.dist-info/entry_points.txt
full_dia-1.0.2.dist-info/top_level.txt
full_dia-1.0.2.dist-info/RECORD
