Metadata-Version: 2.4
Name: full_dia
Version: 1.0.2
Summary: Generate a missingness-free protein quantification matrix from multiple diaPASEF runs through deep learning-based scoring.
Author-email: Jian Song <jian.song.2025@outlook.com>
License-Expression: Apache-2.0
Requires-Python: >=3.10.0
License-File: LICENSE
Requires-Dist: psutil<7.2,>=7.1
Requires-Dist: h5py<3.16,>=3.15
Requires-Dist: matplotlib
Requires-Dist: networkx<3.6,>=3.5
Requires-Dist: numba>=0.63
Requires-Dist: numpy<2.0.0
Requires-Dist: pandas>=2.3
Requires-Dist: pyzstd>=0.19
Requires-Dist: scikit-learn>=1.8
Requires-Dist: scipy>=1.16
Requires-Dist: statsmodels>=0.14
Requires-Dist: pyarrow>=22.0
Requires-Dist: pyyaml>=6.0
Provides-Extra: cuda11
Requires-Dist: cupy-cuda11x==13.3; extra == "cuda11"
Provides-Extra: cuda12
Requires-Dist: cupy-cuda12x==13.3; extra == "cuda12"
Provides-Extra: dev
Requires-Dist: pytest>=6; extra == "dev"
Requires-Dist: flake8; extra == "dev"
Requires-Dist: black; extra == "dev"
Provides-Extra: docs
Requires-Dist: sphinx; extra == "docs"
Requires-Dist: sphinx-rtd-theme; extra == "docs"
Dynamic: license-file
